testfull_pack/README.md
testfull_pack/basehash.py
testfull_pack/file.py
testfull_pack/helpful_test.py
testfull_pack-0.1.3.dist-info/WHEEL
testfull_pack-0.1.3.dist-info/METADATA
testfull_pack-0.1.3.dist-info/RECORD
