Metadata-Version: 2.1
Name: testfull-pack
Version: 0.1.3
Summary: 
Author: Denis Kustov
Requires-Python: >=3.10,<4.0
Classifier: Programming Language :: Python :: 3
Classifier: Programming Language :: Python :: 3.10
Requires-Dist: logsmal (>=0.0.10,<0.0.11)
Requires-Dist: pytest (>=7.1.1,<8.0.0)
